wasserstein/wasserstein.py
wasserstein/config.py
wasserstein/_wasserstein.py
wasserstein/_wasserstein_omp.cpython-311-i386-linux-gnu.so
wasserstein/__init__.py
Wasserstein.libs/libgomp-65f46eca.so.1.0.0
Wasserstein-1.1.0.dist-info/METADATA
Wasserstein-1.1.0.dist-info/top_level.txt
Wasserstein-1.1.0.dist-info/WHEEL
Wasserstein-1.1.0.dist-info/RECORD
Wasserstein-1.1.0.dist-info/LICENSE
